nbplusplus/__init__.py
nbplusplus/_version.py
nbplusplus/extra_builtins.py
nbplusplus/install.py
nbplusplus/ipython_utils.py
nbplusplus/line_magics.py
nbplusplus/run_mode.py
nbplusplus/safety.py
nbplusplus/singletons.py
nbplusplus/types.py
nbplusplus/version.py
nbplusplus/analysis/__init__.py
nbplusplus/analysis/live_refs.py
nbplusplus/analysis/mixins.py
nbplusplus/analysis/reactive_modifiers.py
nbplusplus/analysis/resolved_symbols.py
nbplusplus/analysis/slicing.py
nbplusplus/analysis/symbol_edges.py
nbplusplus/analysis/symbol_ref.py
nbplusplus/analysis/utils.py
nbplusplus/data_model/__init__.py
nbplusplus/data_model/annotation_utils.py
nbplusplus/data_model/code_cell.py
nbplusplus/data_model/data_symbol.py
nbplusplus/data_model/namespace.py
nbplusplus/data_model/scope.py
nbplusplus/data_model/sizing.py
nbplusplus/data_model/timestamp.py
nbplusplus/data_model/update_protocol.py
nbplusplus/kernel/__init__.py
nbplusplus/kernel/__main__.py
nbplusplus/kernel/install.py
nbplusplus/kernel/kernel.py
nbplusplus/resources/kernel/kernel.json
nbplusplus/resources/kernel/logo-32x32.png
nbplusplus/resources/kernel/logo-64x64.png
nbplusplus/resources/labextension/package.json
nbplusplus/resources/labextension/static/549.c5e31d09923c72d47fac.js
nbplusplus/resources/labextension/static/568.e49e9af7479bf07ca2dd.js
nbplusplus/resources/labextension/static/remoteEntry.68632b8bd19cf28f4ec0.js
nbplusplus/resources/labextension/static/style.js
nbplusplus/resources/labextension/static/third-party-licenses.json
nbplusplus/resources/nbextension/index.js
nbplusplus/resources/nbextension/index.js.map
nbplusplus/resources/nbextension/nbplusplus.json
nbplusplus/tracing/__init__.py
nbplusplus/tracing/ast_eavesdrop.py
nbplusplus/tracing/mutation_event.py
nbplusplus/tracing/mutation_special_cases.py
nbplusplus/tracing/safety_ast_rewriter.py
nbplusplus/tracing/stmt_inserter.py
nbplusplus/tracing/stmt_mapper.py
nbplusplus/tracing/symbol_resolver.py
nbplusplus/tracing/trace_events.py
nbpp-0.0.80.dist-info/LICENSE.txt
nbpp-0.0.80.dist-info/METADATA
nbpp-0.0.80.dist-info/WHEEL
nbpp-0.0.80.dist-info/top_level.txt
nbpp-0.0.80.dist-info/RECORD
